LICENSE
git_darcs.py
git_darcs-0.10.1.dist-info/LICENSE
git_darcs-0.10.1.dist-info/METADATA
git_darcs-0.10.1.dist-info/WHEEL
git_darcs-0.10.1.dist-info/entry_points.txt
git_darcs-0.10.1.dist-info/RECORD
