Metadata-Version: 2.1
Name: git-darcs
Version: 0.10.1
Summary:  Incremental import of git into darcs and back again
Home-page: https://github.com/ganwell/git-darcs
License: AGPL-3.0-or-later
Keywords: git,darcs,import,incremental
Author: Jean-Louis Fuchs
Author-email: safe.pen2857@rhizoome.ch
Requires-Python: >=3.10,<4.0
Classifier: Environment :: Console
Classifier: License :: OSI Approved :: GNU Affero General Public License v3 or later (AGPLv3+)
Classifier: Operating System :: POSIX
Classifier: Programming Language :: Python :: 3
Classifier: Programming Language :: Python :: 3.10
Classifier: Programming Language :: Python :: 3.11
Classifier: Programming Language :: Python :: 3.12
Classifier: Topic :: Software Development
Classifier: Topic :: Software Development :: Version Control
Requires-Dist: click (>=8.1.3,<9.0.0)
Requires-Dist: colorama (>=0.4.5,<0.5.0)
Requires-Dist: readchar (>=4.0.3,<5.0.0)
Requires-Dist: tqdm (>=4.64.0,<5.0.0)
Project-URL: Repository, https://github.com/ganwell/git-darcs
